odoo10_addon_website_crm_quick_answer-10.0.1.0.0-py2.7-nspkg.pth
odoo/addons/website_crm_quick_answer/README.rst
odoo/addons/website_crm_quick_answer/__init__.py
odoo/addons/website_crm_quick_answer/__manifest__.py
odoo/addons/website_crm_quick_answer/data/automation.xml
odoo/addons/website_crm_quick_answer/i18n/ca.po
odoo/addons/website_crm_quick_answer/i18n/de.po
odoo/addons/website_crm_quick_answer/i18n/el_GR.po
odoo/addons/website_crm_quick_answer/i18n/es.po
odoo/addons/website_crm_quick_answer/i18n/fr.po
odoo/addons/website_crm_quick_answer/i18n/it.po
odoo/addons/website_crm_quick_answer/i18n/pt_BR.po
odoo/addons/website_crm_quick_answer/i18n/sl.po
odoo/addons/website_crm_quick_answer/static/description/icon.png
odoo10_addon_website_crm_quick_answer-10.0.1.0.0.dist-info/DESCRIPTION.rst
odoo10_addon_website_crm_quick_answer-10.0.1.0.0.dist-info/METADATA
odoo10_addon_website_crm_quick_answer-10.0.1.0.0.dist-info/RECORD
odoo10_addon_website_crm_quick_answer-10.0.1.0.0.dist-info/WHEEL
odoo10_addon_website_crm_quick_answer-10.0.1.0.0.dist-info/metadata.json
odoo10_addon_website_crm_quick_answer-10.0.1.0.0.dist-info/namespace_packages.txt
odoo10_addon_website_crm_quick_answer-10.0.1.0.0.dist-info/top_level.txt
